dxl_py/__init__.py
dxl_py/servos.py
dxl_py/test_servos.py
dxl_py/test_wrapper.py
dxl_py/wrapper.py
dxl_py-0.1.dist-info/LICENSE
dxl_py-0.1.dist-info/METADATA
dxl_py-0.1.dist-info/WHEEL
dxl_py-0.1.dist-info/top_level.txt
dxl_py-0.1.dist-info/RECORD
