Metadata-Version: 2.1
Name: dxl-py
Version: 0.1
Summary: Dynamixel SDK Python Wrapper
Home-page: https://github.com/HugoCMU/dxl_py.git
Author: Hugo Ponte
License: MIT
Platform: UNKNOWN
Classifier: Programming Language :: Python :: 3
Classifier: License :: OSI Approved :: MIT License
Classifier: Operating System :: OS Independent
